[{

    "title": "NLW 5 - Flutter",
    "images": "blocks",
    "questionAnswered": 1,
    "level": "fácil",
    "questions": [{

        "title": "1 - Está curtindo o Flutter?",
        "awnsers": [{
                "title": "Amando o Flutter"
            },
            {
                "title": "Muito TOP"
            },
            {
                "title": "Estou curtindo"
            },
            {
                "title": "Show de bola"
            }
        ]
    }, {

        "title": "2 - Está curtindo o Flutter?",
        "awnsers": [{
                "title": "Amando o Flutter"
            },
            {
                "title": "Muito TOP"
            },
            {
                "title": "Estou curtindo"
            },
            {
                "title": "Show de bola"
            }
        ]
    }]
}]